{"stat.useItem.minecraft.bow":26,"stat.useItem.minecraft.stone":11,"stat.useItem.minecraft.repeater":2,"stat.leaveGame":2,"stat.useItem.minecraft.skull":1,"stat.useItem.minecraft.tnt_minecart":311,"stat.useItem.minecraft.heavy_weighted_pressure_plate":1,"stat.useItem.minecraft.glowstone":260,"stat.useItem.minecraft.bedrock":13,"stat.jump":448,"stat.swimOneCm":13369,"stat.useItem.minecraft.sand":2,"stat.crouchOneCm":712,"stat.useItem.minecraft.redstone_torch":80,"stat.useItem.minecraft.obsidian":352,"stat.useItem.minecraft.dirt":10,"stat.useItem.minecraft.stone_button":8,"stat.useItem.minecraft.light_weighted_pressure_plate":5,"achievement.exploreAllBiomes":{"value":0,"progress":["DesertHills","Desert M","Jungle","River","JungleEdge","Desert","Savanna M","Savanna"]},"stat.useItem.minecraft.dispenser":5,"stat.useItem.minecraft.activator_rail":46,"stat.useItem.minecraft.golden_rail":209,"stat.useItem.minecraft.detector_rail":4,"stat.damageTaken":320,"stat.useItem.minecraft.rail":39,"stat.flyOneCm":749422,"stat.damageDealt":195,"stat.timeSinceDeath":26795,"stat.killEntity.Cow":1,"stat.useItem.minecraft.spawn_egg":5,"stat.useItem.minecraft.iron_door":2,"stat.walkOneCm":189315,"stat.useItem.minecraft.lever":4,"stat.useItem.minecraft.tnt":234,"stat.killEntity.Creeper":1,"stat.minecartOneCm":164494,"stat.useItem.minecraft.minecart":47,"stat.useItem.minecraft.redstone_block":1,"stat.useItem.minecraft.redstone":55,"achievement.mineWood":1,"stat.killEntity.Squid":2,"stat.useItem.minecraft.dropper":7,"stat.sprintOneCm":1183,"stat.killEntity.Skeleton":1,"achievement.openInventory":78,"stat.useItem.minecraft.flint_and_steel":11,"stat.killEntity.Spider":3,"stat.useItem.minecraft.wooden_button":4,"stat.useItem.minecraft.daylight_detector":6,"stat.mobKills":9,"stat.useItem.minecraft.monster_egg":5,"stat.deaths":1,"stat.useItem.minecraft.spruce_door":2,"stat.drop":31,"stat.useItem.minecraft.furnace_minecart":1,"stat.playOneMinute":190839,"stat.useItem.minecraft.diamond_ore":466,"stat.killEntity.Zombie":1,"stat.diveOneCm":27902}